{
    "navLabel": "下载链接",
    "metadata": {
        "title": "欧易pc下载链接：{year} 官方备用及最新分发直链地址",
        "description": "欧易(OKX)资深粉丝实时整理的官方 PC 下载直连链接。为您提供 2026 最新官方分发网址，支持 Windows .exe 与 Mac .dmg 文件的极速获取，规避网络访问障碍。"
    },
    "hero": {
        "title": "欧易 PC 版官方最新下载链接",
        "subtitle": "官方直连 | 极速 CDN | 粉丝同步更新 | 杜绝假冒钓鱼 | {year} 入口",
        "cta": "点击获取下载直链"
    },
    "intro": {
        "title": "链接的价值：如何通过正确入口抵达安全目的地",
        "content": [
            "在互联网环境中，一个错误的链接往往意味着整个账户体系的沦陷。由于部分主域名在特定网络环境下可能存在解析不稳定，或被恶意拦截的情况，欧易官方会不定期分发多组‘官方分发直链’。作为粉丝团队，我们的核心工作就是实时拨测这些由官方正式签发的下载路径，并将它们汇总到这篇《欧易 PC 下载链接》汇总表中，确保您的下载由于‘找不到地址’而中断。",
            "本页面不托管任何安装包，只分享来自官方原装下载服务器的原始 URL。这意味着您点击下载后，数据将直接从欧易全球 CDN 节点流入您的本地设备。我们不仅同步链接，还会教您如何识别链接中的官方特征（如 OKX.com 及其合规二级域名），帮助您在海量的搜索垃圾信息中筛选出真正可信的‘财富通道’。"
        ]
    },
    "sections": [
        {
            "title": "Windows 官方备用直链",
            "description": "针对 Windows 10/11 处理，同步官方最新的 64 位稳定版二进制链接。支持多线程下载加速，确保即使在网络拥塞时段也能顺畅获取 200MB+ 的完整安装镜像。"
        },
        {
            "title": "macOS 官方架构自适应链接",
            "description": "同步苹果系统的 .dmg 官方原装链接。无论您的设备是老款 Intel 芯片还是最新的 M1/M2/M3，点击后系统会自动分发适配您主板架构的最佳安装包版本。"
        }
    ],
    "faq": {
        "title": "关于下载链接的安全性自查",
        "items": [
            {
                "question": "链接失效了怎么办？多久更新一次？",
                "answer": "由于网络对抗和分发策略的调整，部分链接确实会有‘生命周期’。作为资深粉丝群，我们会在链接无法调取后的 15 分钟内进行自动切换或手动修复。建议您将本页加入书签，确保随时能调取活跃的官方直连入口。"
            },
            {
                "question": "点击链接后没有弹出下载框？",
                "answer": "请检查浏览器是否存在‘静默阻止’行为，部分杀毒软件插件可能会拦截外部直接触发的 .exe 下载。您可以尝试复制链接到浏览器的地址栏并按回车直接访问，或使用右键‘另存为’功能。"
            }
        ]
    }
}